powermanim/__init__.py
powermanim/_version.py
powermanim/components/__init__.py
powermanim/components/chartbars.py
powermanim/components/directionalarrow.py
powermanim/components/groupactivable.py
powermanim/components/invariance.py
powermanim/components/logo.py
powermanim/components/numberslider.py
powermanim/layouts/__init__.py
powermanim/layouts/arrangedbullets.py
powermanim/layouts/switchpalette.py
powermanim/scripts/build_anims
powermanim/showcase/__init__.py
powermanim/showcase/showcasescene.py
powermanim/showcase/components/__init__.py
powermanim/showcase/components/chartbars.py
powermanim/showcase/components/directionalarrow.py
powermanim/showcase/components/groupactivable.py
powermanim/showcase/components/invariance.py
powermanim/showcase/components/numberslider.py
powermanim/showcase/layouts/__init__.py
powermanim/showcase/layouts/arrangedbullets.py
powermanim/showcase/layouts/switchpalette.py
powermanim/showcase/templates/__init__.py
powermanim/showcase/templates/bulletlist.py
powermanim/showcase/templates/reference.py
powermanim/showcase/templates/sectiontitle.py
powermanim/templates/__init__.py
powermanim/templates/bulletlist.py
powermanim/templates/reference.py
powermanim/templates/sectiontitle.py
powermanim-0.1.2.data/scripts/build_anims
powermanim-0.1.2.dist-info/LICENSE
powermanim-0.1.2.dist-info/METADATA
powermanim-0.1.2.dist-info/WHEEL
powermanim-0.1.2.dist-info/top_level.txt
powermanim-0.1.2.dist-info/RECORD
